<?xml version="1.0" encoding="UTF-8"?>

<!-- generated on 2025-10-12 11:19:46.803847 by osmWebWizard.py UNKNOWN
<configuration>
    <net-file value="/home/junaith/Sumo/2025-10-12-11-19-37/osm.net.xml.gz"/>
    <output-trip-file value="/home/junaith/Sumo/2025-10-12-11-19-37/osm.passenger.trips.xml"/>
    <route-file value="/home/junaith/Sumo/2025-10-12-11-19-37/osm.passenger.rou.xml"/>
    <prefix value="veh"/>
    <trip-attributes value="departLane=&quot;best&quot;"/>
    <fringe-start-attributes value="departSpeed=&quot;max&quot;"/>
    <vehicle-class value="passenger"/>
    <lanes value="True"/>
    <fringe-factor value="5"/>
    <allow-fringe.min-length value="1000.0"/>
    <edge-permission value="passenger"/>
    <via-edge-types value="highway.motorway,highway.motorway_link,highway.trunk_link,highway.primary_link,highway.secondary_link,highway.tertiary_link"/>
    <min-distance value="300.0"/>
    <min-distance.fringe value="10.0"/>
    <remove-loops value="True"/>
    <insertion-density value="12.0"/>
</configuration>
-->

<routes xmlns:xsi="http://www.w3.org/2001/XMLSchema-instance" xsi:noNamespaceSchemaLocation="http://sumo.dlr.de/xsd/routes_file.xsd">
    <vType id="veh_passenger" vClass="passenger"/>
    <trip id="veh0" depart="0.00" from="208957209#11" to="-161964128#7" departLane="best" type="veh_passenger"/>
    <trip id="veh1" depart="8.18" from="483862449#0" to="208957229#1" departLane="best" type="veh_passenger" departSpeed="max"/>
    <trip id="veh2" depart="16.37" from="804561974#2" to="-208944612#2" departLane="best" type="veh_passenger"/>
    <trip id="veh3" depart="24.55" from="-84168568#3" to="-208944506" departLane="best" type="veh_passenger"/>
    <trip id="veh4" depart="32.74" from="-208957229#2" to="208944509" departLane="best" type="veh_passenger" departSpeed="max"/>
    <trip id="veh5" depart="40.92" from="-161964128#0" to="-208957274#2" departLane="best" type="veh_passenger"/>
    <trip id="veh6" depart="49.10" from="208957229#1" to="208944584" departLane="best" type="veh_passenger"/>
    <trip id="veh7" depart="57.29" from="-208957229#2" to="208944625#2" departLane="best" type="veh_passenger" departSpeed="max"/>
    <trip id="veh8" depart="65.47" from="800384651" to="-1076498443" departLane="best" type="veh_passenger" departSpeed="max"/>
    <trip id="veh9" depart="73.65" from="-800384656" to="-208957209#1" departLane="best" type="veh_passenger" departSpeed="max"/>
    <trip id="veh10" depart="81.84" from="96235945#4" to="-800593534" departLane="best" type="veh_passenger"/>
    <trip id="veh11" depart="90.02" from="803850502" to="208944641#4" departLane="best" type="veh_passenger" departSpeed="max"/>
    <trip id="veh12" depart="98.21" from="208944593#0" to="96236048#1" departLane="best" type="veh_passenger" departSpeed="max"/>
    <trip id="veh13" depart="106.39" from="-803569312" to="208944597" departLane="best" type="veh_passenger" departSpeed="max"/>
    <trip id="veh14" depart="114.57" from="803757414" to="208944656#6" departLane="best" type="veh_passenger" departSpeed="max"/>
    <trip id="veh15" depart="122.76" from="804561973#0" to="208944612#1" departLane="best" type="veh_passenger" departSpeed="max"/>
    <trip id="veh16" depart="130.94" from="-208957237#1" to="-800324731" departLane="best" type="veh_passenger" departSpeed="max"/>
    <trip id="veh17" depart="139.12" from="-208944597" to="-800316117#0" departLane="best" type="veh_passenger" departSpeed="max"/>
    <trip id="veh18" depart="147.31" from="208957209#0" to="-804561974#3" departLane="best" type="veh_passenger"/>
    <trip id="veh19" depart="155.49" from="-803569310#2" to="-228698378#1" departLane="best" type="veh_passenger"/>
    <trip id="veh20" depart="163.68" from="-32111480#5" to="84168568#6" departLane="best" type="veh_passenger" departSpeed="max"/>
    <trip id="veh21" depart="171.86" from="208957209#9" to="208944646#3" departLane="best" type="veh_passenger"/>
    <trip id="veh22" depart="180.04" from="-208944670#1" to="22996884#4" departLane="best" type="veh_passenger" departSpeed="max"/>
    <trip id="veh23" depart="188.23" from="-208944657#1" to="-84168568#10" departLane="best" type="veh_passenger"/>
    <trip id="veh24" depart="196.41" from="96236068#2" to="208944679#2" departLane="best" type="veh_passenger"/>
    <trip id="veh25" depart="204.59" from="208944606#0" to="208957229#2" departLane="best" type="veh_passenger" departSpeed="max"/>
    <trip id="veh26" depart="212.78" from="803850500" to="800316120" departLane="best" type="veh_passenger"/>
    <trip id="veh27" depart="220.96" from="-208957237#1" to="-208944509" departLane="best" type="veh_passenger" departSpeed="max"/>
    <trip id="veh28" depart="229.15" from="-208957209#6" to="84168568#8" departLane="best" type="veh_passenger"/>
    <trip id="veh29" depart="237.33" from="804561973#0" to="-800324749" departLane="best" type="veh_passenger" departSpeed="max"/>
    <trip id="veh30" depart="245.51" from="84168568#2" to="1075652205#1" departLane="best" type="veh_passenger"/>
    <trip id="veh31" depart="253.70" from="208944635#3" to="803853163" departLane="best" type="veh_passenger"/>
    <trip id="veh32" depart="261.88" from="-803853166" to="-483862424" departLane="best" type="veh_passenger"/>
    <trip id="veh33" depart="270.07" from="-208944584" to="-208944549#0" departLane="best" type="veh_passenger" departSpeed="max"/>
    <trip id="veh34" depart="278.25" from="-208944605#0" to="208944663#1" departLane="best" type="veh_passenger"/>
    <trip id="veh35" depart="286.43" from="800324749" to="-96235944#6" departLane="best" type="veh_passenger" departSpeed="max"/>
    <trip id="veh36" depart="294.62" from="-208944546" to="-84168568#11" departLane="best" type="veh_passenger" departSpeed="max"/>
    <trip id="veh37" depart="302.80" from="96236068#4" to="208944551#1" departLane="best" type="veh_passenger"/>
    <trip id="veh38" depart="310.98" from="96236010#5" to="803757415" departLane="best" type="veh_passenger"/>
    <trip id="veh39" depart="319.17" from="-1200726406" to="22996884#1" departLane="best" type="veh_passenger" departSpeed="max"/>
    <trip id="veh40" depart="327.35" from="208957283" to="208944570#1" departLane="best" type="veh_passenger" departSpeed="max"/>
    <trip id="veh41" depart="335.54" from="-32111480#5" to="208944679#3" departLane="best" type="veh_passenger" departSpeed="max"/>
    <trip id="veh42" depart="343.72" from="-208944606#1" to="-96235956#0" departLane="best" type="veh_passenger" departSpeed="max"/>
    <trip id="veh43" depart="351.90" from="-96235945#3" to="96235897#4" departLane="best" type="veh_passenger"/>
    <trip id="veh44" depart="360.09" from="804561973#0" to="-483862455#0" departLane="best" type="veh_passenger" departSpeed="max"/>
    <trip id="veh45" depart="368.27" from="161964128#8" to="-208957247" departLane="best" type="veh_passenger"/>
    <trip id="veh46" depart="376.45" from="84168568#2" to="803850494" departLane="best" type="veh_passenger"/>
    <trip id="veh47" depart="384.64" from="800316118" to="208944579#1" departLane="best" type="veh_passenger" departSpeed="max"/>
    <trip id="veh48" depart="392.82" from="800324737" to="208944551#1" departLane="best" type="veh_passenger" departSpeed="max"/>
    <trip id="veh49" depart="401.01" from="-1059873643" to="-800344956" departLane="best" type="veh_passenger"/>
    <trip id="veh50" depart="409.19" from="804561973#0" to="800593535" departLane="best" type="veh_passenger" departSpeed="max"/>
    <trip id="veh51" depart="417.37" from="-800324738" to="-208944579#1" departLane="best" type="veh_passenger" departSpeed="max"/>
    <trip id="veh52" depart="425.56" from="804561973#0" to="84168568#9" departLane="best" type="veh_passenger" departSpeed="max"/>
    <trip id="veh53" depart="433.74" from="-208944584" to="161964128#12" departLane="best" type="veh_passenger" departSpeed="max"/>
    <trip id="veh54" depart="441.93" from="800316118" to="-208944657#0" departLane="best" type="veh_passenger" departSpeed="max"/>
    <trip id="veh55" depart="450.11" from="1059873643" to="208944597" departLane="best" type="veh_passenger"/>
    <trip id="veh56" depart="458.29" from="-32111480#4" to="803850495#1" departLane="best" type="veh_passenger"/>
    <trip id="veh57" depart="466.48" from="-84168568#4" to="-32111480#0" departLane="best" type="veh_passenger"/>
    <trip id="veh58" depart="474.66" from="208944593#0" to="22996884#4" departLane="best" type="veh_passenger" departSpeed="max"/>
    <trip id="veh59" depart="482.84" from="-84168568#9" to="208944546" departLane="best" type="veh_passenger"/>
    <trip id="veh60" depart="491.03" from="-208944612#2" to="-483862436" departLane="best" type="veh_passenger"/>
    <trip id="veh61" depart="499.21" from="-208957237#1" to="-483862424" departLane="best" type="veh_passenger" departSpeed="max"/>
    <trip id="veh62" depart="507.40" from="-208944551#1" to="208944670#0" departLane="best" type="veh_passenger" departSpeed="max"/>
    <trip id="veh63" depart="515.58" from="-208957237#1" to="804561973#4" departLane="best" type="veh_passenger" departSpeed="max"/>
    <trip id="veh64" depart="523.76" from="803853166" to="-208944602" departLane="best" type="veh_passenger"/>
    <trip id="veh65" depart="531.95" from="-208957214" to="-208944663#1" departLane="best" type="veh_passenger"/>
    <trip id="veh66" depart="540.13" from="96235897#0" to="208944606#1" departLane="best" type="veh_passenger"/>
    <trip id="veh67" depart="548.31" from="-96236048#8" to="800324732" departLane="best" type="veh_passenger"/>
    <trip id="veh68" depart="556.50" from="800384651" to="-208957267#1" departLane="best" type="veh_passenger" departSpeed="max"/>
    <trip id="veh69" depart="564.68" from="-208944597" to="-96235956#0" departLane="best" type="veh_passenger" departSpeed="max"/>
    <trip id="veh70" depart="572.87" from="483862446#0" to="208957209#7" departLane="best" type="veh_passenger" departSpeed="max"/>
    <trip id="veh71" depart="581.05" from="-804561974#1" to="-800593536#1" departLane="best" type="veh_passenger"/>
    <trip id="veh72" depart="589.23" from="804561973#0" to="-483862446#0" departLane="best" type="veh_passenger" departSpeed="max"/>
    <trip id="veh73" depart="597.42" from="-208944682#4" to="-96236048#5" departLane="best" type="veh_passenger"/>
    <trip id="veh74" depart="605.60" from="-208957274#0" to="84168568#11" departLane="best" type="veh_passenger"/>
    <trip id="veh75" depart="613.78" from="-96235897#3" to="803757415" departLane="best" type="veh_passenger"/>
    <trip id="veh76" depart="621.97" from="208944602" to="-208944565#0" departLane="best" type="veh_passenger" departSpeed="max"/>
    <trip id="veh77" depart="630.15" from="96236010#3" to="84168568#2" departLane="best" type="veh_passenger"/>
    <trip id="veh78" depart="638.34" from="-804561974#0" to="-208944585" departLane="best" type="veh_passenger"/>
    <trip id="veh79" depart="646.52" from="-803569312" to="96236068#0" departLane="best" type="veh_passenger" departSpeed="max"/>
    <trip id="veh80" depart="654.70" from="-32111480#4" to="800324732" departLane="best" type="veh_passenger"/>
    <trip id="veh81" depart="662.89" from="-96235945#4" to="-96235944#7" departLane="best" type="veh_passenger"/>
    <trip id="veh82" depart="671.07" from="96235945#4" to="96236068#4" departLane="best" type="veh_passenger"/>
    <trip id="veh83" depart="679.26" from="208944606#0" to="228698378#2" departLane="best" type="veh_passenger" departSpeed="max"/>
    <trip id="veh84" depart="687.44" from="-208944656#6" to="-800324737" departLane="best" type="veh_passenger" departSpeed="max"/>
    <trip id="veh85" depart="695.62" from="96236010#2" to="208944615#0" departLane="best" type="veh_passenger"/>
    <trip id="veh86" depart="703.81" from="-208944524" to="208944623#1" departLane="best" type="veh_passenger"/>
    <trip id="veh87" depart="711.99" from="208944503" to="803569312" departLane="best" type="veh_passenger"/>
    <trip id="veh88" depart="720.17" from="-208944656#6" to="96235945#0" departLane="best" type="veh_passenger" departSpeed="max"/>
    <trip id="veh89" depart="728.36" from="-208944568" to="-208957266" departLane="best" type="veh_passenger"/>
    <trip id="veh90" depart="736.54" from="208944646#2" to="208957209#9" departLane="best" type="veh_passenger"/>
    <trip id="veh91" depart="744.73" from="-208957241#1" to="-208944656#0" departLane="best" type="veh_passenger"/>
    <trip id="veh92" depart="752.91" from="804561974#0" to="-483862438" departLane="best" type="veh_passenger"/>
    <trip id="veh93" depart="761.09" from="-84168568#2" to="208944623#1" departLane="best" type="veh_passenger"/>
    <trip id="veh94" depart="769.28" from="208944551#0" to="84168568#5" departLane="best" type="veh_passenger"/>
    <trip id="veh95" depart="777.46" from="-208957209#10" to="228698378#1" departLane="best" type="veh_passenger"/>
    <trip id="veh96" depart="785.64" from="-208944551#1" to="-32111480#1" departLane="best" type="veh_passenger" departSpeed="max"/>
    <trip id="veh97" depart="793.83" from="-32111480#4" to="84168568#4" departLane="best" type="veh_passenger"/>
    <trip id="veh98" depart="802.01" from="803850471#1" to="208957267#0" departLane="best" type="veh_passenger"/>
    <trip id="veh99" depart="810.20" from="208944663#0" to="96236068#1" departLane="best" type="veh_passenger"/>
    <trip id="veh100" depart="818.38" from="800593536#1" to="-800324737" departLane="best" type="veh_passenger"/>
    <trip id="veh101" depart="826.56" from="208957266" to="84168568#6" departLane="best" type="veh_passenger" departSpeed="max"/>
    <trip id="veh102" depart="834.75" from="-208944600" to="208944597" departLane="best" type="veh_passenger" departSpeed="max"/>
    <trip id="veh103" depart="842.93" from="-483862437#1" to="208944641#4" departLane="best" type="veh_passenger"/>
    <trip id="veh104" depart="851.11" from="483862437#1" to="-208957283" departLane="best" type="veh_passenger"/>
    <trip id="veh105" depart="859.30" from="208944699#4" to="-483862455#0" departLane="best" type="veh_passenger"/>
    <trip id="veh106" depart="867.48" from="161964128#10" to="804561973#4" departLane="best" type="veh_passenger"/>
    <trip id="veh107" depart="875.67" from="-84168568#4" to="-800316116" departLane="best" type="veh_passenger"/>
    <trip id="veh108" depart="883.85" from="-1075652205#0" to="800316117#1" departLane="best" type="veh_passenger"/>
    <trip id="veh109" depart="892.03" from="208957209#1" to="-483862449#1" departLane="best" type="veh_passenger"/>
    <trip id="veh110" depart="900.22" from="483862449#1" to="208944597" departLane="best" type="veh_passenger"/>
    <trip id="veh111" depart="908.40" from="84168568#1" to="208944584" departLane="best" type="veh_passenger"/>
    <trip id="veh112" depart="916.59" from="803850471#1" to="208944623#0" departLane="best" type="veh_passenger"/>
    <trip id="veh113" depart="924.77" from="-208944646#3" to="-208944657#0" departLane="best" type="veh_passenger"/>
    <trip id="veh114" depart="932.95" from="-800324738" to="803853163" departLane="best" type="veh_passenger" departSpeed="max"/>
    <trip id="veh115" depart="941.14" from="800324749" to="803757415" departLane="best" type="veh_passenger" departSpeed="max"/>
    <trip id="veh116" depart="949.32" from="-208957274#0" to="-208944635#1" departLane="best" type="veh_passenger"/>
    <trip id="veh117" depart="957.50" from="-804561974#4" to="208944656#6" departLane="best" type="veh_passenger"/>
    <trip id="veh118" depart="965.69" from="-208944656#6" to="84168568#3" departLane="best" type="veh_passenger" departSpeed="max"/>
    <trip id="veh119" depart="973.87" from="804561973#0" to="96236048#3" departLane="best" type="veh_passenger" departSpeed="max"/>
    <trip id="veh120" depart="982.06" from="-1252215163" to="22996884#4" departLane="best" type="veh_passenger"/>
    <trip id="veh121" depart="990.24" from="-800344954#2" to="84168568#3" departLane="best" type="veh_passenger" departSpeed="max"/>
    <trip id="veh122" depart="998.42" from="800384651" to="-483862455#0" departLane="best" type="veh_passenger" departSpeed="max"/>
    <trip id="veh123" depart="1006.61" from="800324742" to="-208944641#1" departLane="best" type="veh_passenger" departSpeed="max"/>
    <trip id="veh124" depart="1014.79" from="804561973#0" to="803569312" departLane="best" type="veh_passenger" departSpeed="max"/>
    <trip id="veh125" depart="1022.97" from="-208957229#2" to="800344954#2" departLane="best" type="veh_passenger" departSpeed="max"/>
    <trip id="veh126" depart="1031.16" from="-96236010#4" to="-800324742" departLane="best" type="veh_passenger"/>
    <trip id="veh127" depart="1039.34" from="800324749" to="-483862436" departLane="best" type="veh_passenger" departSpeed="max"/>
    <trip id="veh128" depart="1047.53" from="-1220119128" to="-208957273#0" departLane="best" type="veh_passenger"/>
    <trip id="veh129" depart="1055.71" from="-800344954#2" to="803757415" departLane="best" type="veh_passenger" departSpeed="max"/>
    <trip id="veh130" depart="1063.89" from="96236048#8" to="208944570#1" departLane="best" type="veh_passenger"/>
    <trip id="veh131" depart="1072.08" from="96235897#4" to="-208944656#0" departLane="best" type="veh_passenger"/>
    <trip id="veh132" depart="1080.26" from="96236010#5" to="-208957246#1" departLane="best" type="veh_passenger"/>
    <trip id="veh133" depart="1088.45" from="96235956#0" to="-483862455#0" departLane="best" type="veh_passenger" departSpeed="max"/>
    <trip id="veh134" depart="1096.63" from="-208944600" to="-96235956#0" departLane="best" type="veh_passenger" departSpeed="max"/>
    <trip id="veh135" depart="1104.81" from="483862446#0" to="-800324749" departLane="best" type="veh_passenger" departSpeed="max"/>
    <trip id="veh136" depart="1113.00" from="208944656#3" to="208944524" departLane="best" type="veh_passenger"/>
    <trip id="veh137" depart="1121.18" from="-803757415" to="208944612#1" departLane="best" type="veh_passenger" departSpeed="max"/>
    <trip id="veh138" depart="1129.36" from="-228698378#0" to="208957273#1" departLane="best" type="veh_passenger"/>
    <trip id="veh139" depart="1137.55" from="-1075008630" to="84168568#2" departLane="best" type="veh_passenger"/>
    <trip id="veh140" depart="1145.73" from="208944593#0" to="22996884#1" departLane="best" type="veh_passenger" departSpeed="max"/>
    <trip id="veh141" depart="1153.92" from="483862455#0" to="208957209#5" departLane="best" type="veh_passenger" departSpeed="max"/>
    <trip id="veh142" depart="1162.10" from="-803569305" to="-208944602" departLane="best" type="veh_passenger" departSpeed="max"/>
    <trip id="veh143" depart="1170.28" from="208957266" to="-800384651" departLane="best" type="veh_passenger" departSpeed="max"/>
    <trip id="veh144" depart="1178.47" from="-800324738" to="803569310#2" departLane="best" type="veh_passenger" departSpeed="max"/>
    <trip id="veh145" depart="1186.65" from="483862438" to="-800324737" departLane="best" type="veh_passenger" departSpeed="max"/>
    <trip id="veh146" depart="1194.83" from="-800324738" to="-96235897#2" departLane="best" type="veh_passenger" departSpeed="max"/>
    <trip id="veh147" depart="1203.02" from="-208944625#0" to="-96235944#4" departLane="best" type="veh_passenger"/>
    <trip id="veh148" depart="1211.20" from="96235897#4" to="208957229#1" departLane="best" type="veh_passenger"/>
    <trip id="veh149" depart="1219.39" from="805249587" to="208944656#5" departLane="best" type="veh_passenger" departSpeed="max"/>
    <trip id="veh150" depart="1227.57" from="-800316121" to="208944585" departLane="best" type="veh_passenger"/>
    <trip id="veh151" depart="1235.75" from="-1059873643" to="-800316121" departLane="best" type="veh_passenger"/>
    <trip id="veh152" depart="1243.94" from="-84168568#6" to="208944615#0" departLane="best" type="veh_passenger"/>
    <trip id="veh153" depart="1252.12" from="208957241#0" to="1200726406" departLane="best" type="veh_passenger"/>
    <trip id="veh154" depart="1260.30" from="-96235897#2" to="-32111480#1" departLane="best" type="veh_passenger"/>
    <trip id="veh155" depart="1268.49" from="-96236048#8" to="803853166" departLane="best" type="veh_passenger"/>
    <trip id="veh156" depart="1276.67" from="800324749" to="-208957237#0" departLane="best" type="veh_passenger" departSpeed="max"/>
    <trip id="veh157" depart="1284.86" from="-208944579#1" to="208944546" departLane="best" type="veh_passenger"/>
    <trip id="veh158" depart="1293.04" from="208944699#3" to="-800384651" departLane="best" type="veh_passenger"/>
    <trip id="veh159" depart="1301.22" from="803569310#0" to="483862437#1" departLane="best" type="veh_passenger"/>
    <trip id="veh160" depart="1309.41" from="208957273#0" to="-483862436" departLane="best" type="veh_passenger"/>
    <trip id="veh161" depart="1317.59" from="-208944699#4" to="-161964128#7" departLane="best" type="veh_passenger"/>
    <trip id="veh162" depart="1325.78" from="803850502" to="-208944602" departLane="best" type="veh_passenger" departSpeed="max"/>
    <trip id="veh163" depart="1333.96" from="-84168568#11" to="208944670#0" departLane="best" type="veh_passenger"/>
    <trip id="veh164" depart="1342.14" from="-208944699#0" to="208957241#1" departLane="best" type="veh_passenger"/>
    <trip id="veh165" depart="1350.33" from="208957241#1" to="-1076498443" departLane="best" type="veh_passenger"/>
    <trip id="veh166" depart="1358.51" from="800316115" to="800316117#1" departLane="best" type="veh_passenger" departSpeed="max"/>
    <trip id="veh167" depart="1366.69" from="-208944600" to="-96235945#1" departLane="best" type="veh_passenger" departSpeed="max"/>
    <trip id="veh168" depart="1374.88" from="-208944679#0" to="96235944#6" departLane="best" type="veh_passenger"/>
    <trip id="veh169" depart="1383.06" from="-208957274#0" to="803569310#2" departLane="best" type="veh_passenger"/>
    <trip id="veh170" depart="1391.25" from="-96235945#5" to="800324740#0" departLane="best" type="veh_passenger"/>
    <trip id="veh171" depart="1399.43" from="208957266" to="96236068#1" departLane="best" type="veh_passenger" departSpeed="max"/>
    <trip id="veh172" depart="1407.61" from="208944646#3" to="96235897#2" departLane="best" type="veh_passenger"/>
    <trip id="veh173" depart="1415.80" from="804561974#1" to="208944656#3" departLane="best" type="veh_passenger"/>
    <trip id="veh174" depart="1423.98" from="483862438" to="208944509" departLane="best" type="veh_passenger" departSpeed="max"/>
    <trip id="veh175" depart="1432.16" from="803757414" to="208944585" departLane="best" type="veh_passenger" departSpeed="max"/>
    <trip id="veh176" depart="1440.35" from="805249587" to="32111480#4" departLane="best" type="veh_passenger" departSpeed="max"/>
    <trip id="veh177" depart="1448.53" from="-96236048#9" to="-483862449#0" departLane="best" type="veh_passenger"/>
    <trip id="veh178" depart="1456.72" from="-208957273#0" to="208944679#1" departLane="best" type="veh_passenger"/>
    <trip id="veh179" depart="1464.90" from="800316118" to="208944549#1" departLane="best" type="veh_passenger" departSpeed="max"/>
    <trip id="veh180" depart="1473.08" from="208944682#6" to="-800316115" departLane="best" type="veh_passenger"/>
    <trip id="veh181" depart="1481.27" from="-208944565#0" to="-800316119" departLane="best" type="veh_passenger"/>
    <trip id="veh182" depart="1489.45" from="-32111480#5" to="-800344956" departLane="best" type="veh_passenger" departSpeed="max"/>
    <trip id="veh183" depart="1497.63" from="208944593#0" to="-208944682#0" departLane="best" type="veh_passenger" departSpeed="max"/>
    <trip id="veh184" depart="1505.82" from="-208957237#1" to="208957238" departLane="best" type="veh_passenger" departSpeed="max"/>
    <trip id="veh185" depart="1514.00" from="-804561974#6" to="208944584" departLane="best" type="veh_passenger"/>
    <trip id="veh186" depart="1522.19" from="-84168568#11" to="-227850831" departLane="best" type="veh_passenger"/>
    <trip id="veh187" depart="1530.37" from="-84168568#3" to="804561973#4" departLane="best" type="veh_passenger"/>
    <trip id="veh188" depart="1538.55" from="208944635#2" to="208957241#0" departLane="best" type="veh_passenger"/>
    <trip id="veh189" depart="1546.74" from="803850502" to="800316117#0" departLane="best" type="veh_passenger" departSpeed="max"/>
    <trip id="veh190" depart="1554.92" from="-800593536#0" to="483862446#1" departLane="best" type="veh_passenger"/>
    <trip id="veh191" depart="1563.11" from="803850502" to="96235897#4" departLane="best" type="veh_passenger" departSpeed="max"/>
    <trip id="veh192" depart="1571.29" from="-84168568#2" to="32111480#5" departLane="best" type="veh_passenger"/>
    <trip id="veh193" depart="1579.47" from="208944602" to="208944641#3" departLane="best" type="veh_passenger" departSpeed="max"/>
    <trip id="veh194" depart="1587.66" from="-208957229#2" to="-483862424" departLane="best" type="veh_passenger" departSpeed="max"/>
    <trip id="veh195" depart="1595.84" from="-84168568#9" to="-208944503" departLane="best" type="veh_passenger"/>
    <trip id="veh196" depart="1604.02" from="-800384656" to="208957229#2" departLane="best" type="veh_passenger" departSpeed="max"/>
    <trip id="veh197" depart="1612.21" from="-804561974#2" to="-208957209#7" departLane="best" type="veh_passenger"/>
    <trip id="veh198" depart="1620.39" from="-96236048#3" to="-208944657#0" departLane="best" type="veh_passenger"/>
    <trip id="veh199" depart="1628.58" from="208944682#1" to="-161964128#8" departLane="best" type="veh_passenger"/>
    <trip id="veh200" depart="1636.76" from="-803853163" to="208944600" departLane="best" type="veh_passenger" departSpeed="max"/>
    <trip id="veh201" depart="1644.94" from="-161964128#1" to="208944679#3" departLane="best" type="veh_passenger"/>
    <trip id="veh202" depart="1653.13" from="-208944635#1" to="1196331641" departLane="best" type="veh_passenger"/>
    <trip id="veh203" depart="1661.31" from="-208944506" to="-84168568#10" departLane="best" type="veh_passenger"/>
    <trip id="veh204" depart="1669.49" from="-208957209#7" to="-800344957" departLane="best" type="veh_passenger"/>
    <trip id="veh205" depart="1677.68" from="800316115" to="800593535" departLane="best" type="veh_passenger" departSpeed="max"/>
    <trip id="veh206" depart="1685.86" from="-208957274#2" to="-208944606#0" departLane="best" type="veh_passenger"/>
    <trip id="veh207" depart="1694.05" from="208957229#1" to="800316122" departLane="best" type="veh_passenger"/>
    <trip id="veh208" depart="1702.23" from="208957237#0" to="483862446#2" departLane="best" type="veh_passenger"/>
    <trip id="veh209" depart="1710.41" from="96235944#4" to="-208957283" departLane="best" type="veh_passenger"/>
    <trip id="veh210" depart="1718.60" from="-1220118991" to="-208944699#4" departLane="best" type="veh_passenger" departSpeed="max"/>
    <trip id="veh211" depart="1726.78" from="-208944623#1" to="208957209#4" departLane="best" type="veh_passenger"/>
    <trip id="veh212" depart="1734.97" from="208944612#1" to="-483862424" departLane="best" type="veh_passenger"/>
    <trip id="veh213" depart="1743.15" from="32111480#1" to="800316117#1" departLane="best" type="veh_passenger"/>
    <trip id="veh214" depart="1751.33" from="-208944663#2" to="208944646#1" departLane="best" type="veh_passenger"/>
    <trip id="veh215" depart="1759.52" from="803569310#1" to="96235945#4" departLane="best" type="veh_passenger"/>
    <trip id="veh216" depart="1767.70" from="-208944600" to="-161964128#7" departLane="best" type="veh_passenger" departSpeed="max"/>
    <trip id="veh217" depart="1775.88" from="96235945#5" to="-84168568#7" departLane="best" type="veh_passenger"/>
    <trip id="veh218" depart="1784.07" from="483862436" to="-208944605#0" departLane="best" type="veh_passenger" departSpeed="max"/>
    <trip id="veh219" depart="1792.25" from="-208944598#0" to="800316117#1" departLane="best" type="veh_passenger"/>
    <trip id="veh220" depart="1800.44" from="803850502" to="208944641#0" departLane="best" type="veh_passenger" departSpeed="max"/>
    <trip id="veh221" depart="1808.62" from="800324740#1" to="-803569311#2" departLane="best" type="veh_passenger"/>
    <trip id="veh222" depart="1816.80" from="-84168568#6" to="-805249587" departLane="best" type="veh_passenger"/>
    <trip id="veh223" depart="1824.99" from="208944509" to="-803569310#1" departLane="best" type="veh_passenger"/>
    <trip id="veh224" depart="1833.17" from="-208944600" to="96235945#0" departLane="best" type="veh_passenger" departSpeed="max"/>
    <trip id="veh225" depart="1841.35" from="208957209#0" to="800593535" departLane="best" type="veh_passenger"/>
    <trip id="veh226" depart="1849.54" from="483862424" to="-96235956#0" departLane="best" type="veh_passenger" departSpeed="max"/>
    <trip id="veh227" depart="1857.72" from="483862449#0" to="96235945#5" departLane="best" type="veh_passenger" departSpeed="max"/>
    <trip id="veh228" depart="1865.91" from="-32111480#5" to="800324743" departLane="best" type="veh_passenger" departSpeed="max"/>
    <trip id="veh229" depart="1874.09" from="-84168568#8" to="22996884#4" departLane="best" type="veh_passenger"/>
    <trip id="veh230" depart="1882.27" from="-32111480#5" to="803569311#2" departLane="best" type="veh_passenger" departSpeed="max"/>
    <trip id="veh231" depart="1890.46" from="803757414" to="-208944612#2" departLane="best" type="veh_passenger" departSpeed="max"/>
    <trip id="veh232" depart="1898.64" from="804561973#1" to="-483862438" departLane="best" type="veh_passenger"/>
    <trip id="veh233" depart="1906.82" from="-96236048#1" to="208944656#1" departLane="best" type="veh_passenger"/>
    <trip id="veh234" depart="1915.01" from="-803569312" to="-208944503" departLane="best" type="veh_passenger" departSpeed="max"/>
    <trip id="veh235" depart="1923.19" from="803850502" to="-208957266" departLane="best" type="veh_passenger" departSpeed="max"/>
    <trip id="veh236" depart="1931.38" from="32111480#3" to="-800316116" departLane="best" type="veh_passenger"/>
    <trip id="veh237" depart="1939.56" from="-1200726406" to="96235868" departLane="best" type="veh_passenger" departSpeed="max"/>
    <trip id="veh238" depart="1947.74" from="228698378#2" to="208944679#3" departLane="best" type="veh_passenger"/>
    <trip id="veh239" depart="1955.93" from="161964128#11" to="800324736" departLane="best" type="veh_passenger"/>
    <trip id="veh240" depart="1964.11" from="-208944585" to="-483862424" departLane="best" type="veh_passenger"/>
    <trip id="veh241" depart="1972.30" from="22996884#1" to="-800324742" departLane="best" type="veh_passenger"/>
    <trip id="veh242" depart="1980.48" from="208944635#0" to="1220118991" departLane="best" type="veh_passenger"/>
    <trip id="veh243" depart="1988.66" from="208944579#0" to="-96235945#1" departLane="best" type="veh_passenger"/>
    <trip id="veh244" depart="1996.85" from="483862455#0" to="-800384651" departLane="best" type="veh_passenger" departSpeed="max"/>
    <trip id="veh245" depart="2005.03" from="32111480#4" to="-800316115" departLane="best" type="veh_passenger"/>
    <trip id="veh246" depart="2013.21" from="-208957274#1" to="-208944656#0" departLane="best" type="veh_passenger"/>
    <trip id="veh247" depart="2021.40" from="-208944679#3" to="-32111480#3" departLane="best" type="veh_passenger" departSpeed="max"/>
    <trip id="veh248" depart="2029.58" from="1220116022" to="22996884#4" departLane="best" type="veh_passenger"/>
    <trip id="veh249" depart="2037.77" from="96236048#3" to="208944551#1" departLane="best" type="veh_passenger"/>
    <trip id="veh250" depart="2045.95" from="-800316116" to="-208944635#0" departLane="best" type="veh_passenger"/>
    <trip id="veh251" depart="2054.13" from="-208944699#0" to="-483862436" departLane="best" type="veh_passenger"/>
    <trip id="veh252" depart="2062.32" from="-208944679#3" to="-161964128#1" departLane="best" type="veh_passenger" departSpeed="max"/>
    <trip id="veh253" depart="2070.50" from="208944585" to="-800316115" departLane="best" type="veh_passenger"/>
    <trip id="veh254" depart="2078.68" from="96236048#2" to="208944597" departLane="best" type="veh_passenger"/>
    <trip id="veh255" depart="2086.87" from="32111480#0" to="-208944656#5" departLane="best" type="veh_passenger"/>
    <trip id="veh256" depart="2095.05" from="804561973#0" to="161964128#12" departLane="best" type="veh_passenger" departSpeed="max"/>
    <trip id="veh257" depart="2103.24" from="804561973#0" to="208944606#1" departLane="best" type="veh_passenger" departSpeed="max"/>
    <trip id="veh258" depart="2111.42" from="-208944679#3" to="-208944565#0" departLane="best" type="veh_passenger" departSpeed="max"/>
    <trip id="veh259" depart="2119.60" from="96235944#0" to="1220118991" departLane="best" type="veh_passenger" departSpeed="max"/>
    <trip id="veh260" depart="2127.79" from="803569311#0" to="-84168568#8" departLane="best" type="veh_passenger"/>
    <trip id="veh261" depart="2135.97" from="-208944551#1" to="208944670#0" departLane="best" type="veh_passenger" departSpeed="max"/>
    <trip id="veh262" depart="2144.15" from="-208944511" to="-208944699#2" departLane="best" type="veh_passenger"/>
    <trip id="veh263" depart="2152.34" from="208944612#0" to="-800324741" departLane="best" type="veh_passenger"/>
    <trip id="veh264" depart="2160.52" from="96236068#3" to="-208944656#0" departLane="best" type="veh_passenger"/>
    <trip id="veh265" depart="2168.71" from="800316118" to="208944646#1" departLane="best" type="veh_passenger" departSpeed="max"/>
    <trip id="veh266" depart="2176.89" from="800324749" to="-483862436" departLane="best" type="veh_passenger" departSpeed="max"/>
    <trip id="veh267" depart="2185.07" from="208944551#0" to="-96236048#6" departLane="best" type="veh_passenger"/>
    <trip id="veh268" depart="2193.26" from="-96235897#3" to="803757415" departLane="best" type="veh_passenger"/>
    <trip id="veh269" depart="2201.44" from="96236068#2" to="-800324742" departLane="best" type="veh_passenger"/>
    <trip id="veh270" depart="2209.63" from="208944682#0" to="208944646#3" departLane="best" type="veh_passenger"/>
    <trip id="veh271" depart="2217.81" from="483862449#0" to="96235868" departLane="best" type="veh_passenger" departSpeed="max"/>
    <trip id="veh272" depart="2225.99" from="-208957209#4" to="-228698378#2" departLane="best" type="veh_passenger"/>
    <trip id="veh273" depart="2234.18" from="-208944670#1" to="-208944602" departLane="best" type="veh_passenger" departSpeed="max"/>
    <trip id="veh274" depart="2242.36" from="-1075008630" to="-96236048#6" departLane="best" type="veh_passenger"/>
    <trip id="veh275" depart="2250.54" from="208944646#1" to="-800324734" departLane="best" type="veh_passenger"/>
    <trip id="veh276" depart="2258.73" from="32111480#4" to="-96236048#9" departLane="best" type="veh_passenger"/>
    <trip id="veh277" depart="2266.91" from="227850831" to="84168568#11" departLane="best" type="veh_passenger"/>
    <trip id="veh278" depart="2275.10" from="800324742" to="208944657#1" departLane="best" type="veh_passenger" departSpeed="max"/>
    <trip id="veh279" depart="2283.28" from="-84168568#5" to="208944584" departLane="best" type="veh_passenger"/>
    <trip id="veh280" depart="2291.46" from="208957209#9" to="804561973#5" departLane="best" type="veh_passenger"/>
    <trip id="veh281" depart="2299.65" from="803757414" to="-208944602" departLane="best" type="veh_passenger" departSpeed="max"/>
    <trip id="veh282" depart="2307.83" from="-208944663#1" to="-800324742" departLane="best" type="veh_passenger"/>
    <trip id="veh283" depart="2316.01" from="-800316117#1" to="-208944656#3" departLane="best" type="veh_passenger" departSpeed="max"/>
    <trip id="veh284" depart="2324.20" from="228698378#0" to="208957246#1" departLane="best" type="veh_passenger"/>
    <trip id="veh285" depart="2332.38" from="96235944#0" to="161964128#8" departLane="best" type="veh_passenger" departSpeed="max"/>
    <trip id="veh286" depart="2340.57" from="-161964128#3" to="-96235956#0" departLane="best" type="veh_passenger"/>
    <trip id="veh287" depart="2348.75" from="-800324743" to="-483862446#0" departLane="best" type="veh_passenger" departSpeed="max"/>
    <trip id="veh288" depart="2356.93" from="-208944584" to="96235945#0" departLane="best" type="veh_passenger" departSpeed="max"/>
    <trip id="veh289" depart="2365.12" from="803850493#1" to="208944612#0" departLane="best" type="veh_passenger"/>
    <trip id="veh290" depart="2373.30" from="96235944#6" to="96236068#5" departLane="best" type="veh_passenger"/>
    <trip id="veh291" depart="2381.48" from="208957267#2" to="-800316115" departLane="best" type="veh_passenger"/>
    <trip id="veh292" depart="2389.67" from="-96236048#6" to="208944682#4" departLane="best" type="veh_passenger"/>
    <trip id="veh293" depart="2397.85" from="84168568#3" to="-208957266" departLane="best" type="veh_passenger"/>
    <trip id="veh294" depart="2406.04" from="208944635#3" to="208944670#0" departLane="best" type="veh_passenger"/>
    <trip id="veh295" depart="2414.22" from="161964128#2" to="-208944623#0" departLane="best" type="veh_passenger"/>
    <trip id="veh296" depart="2422.40" from="-800593535" to="-800384651" departLane="best" type="veh_passenger" departSpeed="max"/>
    <trip id="veh297" depart="2430.59" from="208957267#1" to="803569312" departLane="best" type="veh_passenger"/>
    <trip id="veh298" depart="2438.77" from="-800344954#2" to="208957238" departLane="best" type="veh_passenger" departSpeed="max"/>
    <trip id="veh299" depart="2446.96" from="-800316117#1" to="84168568#9" departLane="best" type="veh_passenger" departSpeed="max"/>
    <trip id="veh300" depart="2455.14" from="800593534" to="208944597" departLane="best" type="veh_passenger"/>
    <trip id="veh301" depart="2463.32" from="-96235945#4" to="-800324749" departLane="best" type="veh_passenger"/>
    <trip id="veh302" depart="2471.51" from="-800324743" to="96236010#3" departLane="best" type="veh_passenger" departSpeed="max"/>
    <trip id="veh303" depart="2479.69" from="-804561974#2" to="208944546" departLane="best" type="veh_passenger"/>
    <trip id="veh304" depart="2487.87" from="208944593#1" to="-96235944#0" departLane="best" type="veh_passenger"/>
    <trip id="veh305" depart="2496.06" from="-208944682#1" to="-804561974#1" departLane="best" type="veh_passenger"/>
    <trip id="veh306" depart="2504.24" from="800316118" to="-208957283" departLane="best" type="veh_passenger" departSpeed="max"/>
    <trip id="veh307" depart="2512.43" from="208944602" to="84168568#2" departLane="best" type="veh_passenger" departSpeed="max"/>
    <trip id="veh308" depart="2520.61" from="-84168568#9" to="208957246#0" departLane="best" type="veh_passenger"/>
    <trip id="veh309" depart="2528.79" from="-208944612#2" to="96236048#1" departLane="best" type="veh_passenger"/>
    <trip id="veh310" depart="2536.98" from="-208944656#6" to="208944597" departLane="best" type="veh_passenger" departSpeed="max"/>
    <trip id="veh311" depart="2545.16" from="96236068#3" to="804561974#2" departLane="best" type="veh_passenger"/>
    <trip id="veh312" depart="2553.34" from="-96236010#5" to="-208944656#0" departLane="best" type="veh_passenger"/>
    <trip id="veh313" depart="2561.53" from="483862436" to="208944513" departLane="best" type="veh_passenger" departSpeed="max"/>
    <trip id="veh314" depart="2569.71" from="-483862446#1" to="800593535" departLane="best" type="veh_passenger"/>
    <trip id="veh315" depart="2577.90" from="96236048#7" to="-483862438" departLane="best" type="veh_passenger"/>
    <trip id="veh316" depart="2586.08" from="208944602" to="-84168568#2" departLane="best" type="veh_passenger" departSpeed="max"/>
    <trip id="veh317" depart="2594.26" from="84168568#5" to="208944512#0" departLane="best" type="veh_passenger"/>
    <trip id="veh318" depart="2602.45" from="804561973#0" to="803757415" departLane="best" type="veh_passenger" departSpeed="max"/>
    <trip id="veh319" depart="2610.63" from="-483862446#2" to="800324733" departLane="best" type="veh_passenger" departSpeed="max"/>
    <trip id="veh320" depart="2618.82" from="-84168568#11" to="84168568#5" departLane="best" type="veh_passenger"/>
    <trip id="veh321" depart="2627.00" from="208944512#0" to="800384656" departLane="best" type="veh_passenger"/>
    <trip id="veh322" depart="2635.18" from="208944641#0" to="96236068#5" departLane="best" type="veh_passenger"/>
    <trip id="veh323" depart="2643.37" from="161964128#10" to="-208944699#1" departLane="best" type="veh_passenger"/>
    <trip id="veh324" depart="2651.55" from="208944593#0" to="-803569311#1" departLane="best" type="veh_passenger" departSpeed="max"/>
    <trip id="veh325" depart="2659.73" from="208944602" to="208944584" departLane="best" type="veh_passenger" departSpeed="max"/>
    <trip id="veh326" depart="2667.92" from="-96235945#4" to="-800344956" departLane="best" type="veh_passenger"/>
    <trip id="veh327" depart="2676.10" from="-208944682#2" to="208957242" departLane="best" type="veh_passenger"/>
    <trip id="veh328" depart="2684.29" from="208944623#2" to="-483862437#0" departLane="best" type="veh_passenger"/>
    <trip id="veh329" depart="2692.47" from="800324737" to="-208944549#0" departLane="best" type="veh_passenger" departSpeed="max"/>
    <trip id="veh330" depart="2700.65" from="483862455#0" to="208957267#2" departLane="best" type="veh_passenger" departSpeed="max"/>
    <trip id="veh331" depart="2708.84" from="800384651" to="-84168568#3" departLane="best" type="veh_passenger" departSpeed="max"/>
    <trip id="veh332" depart="2717.02" from="208957266" to="800384656" departLane="best" type="veh_passenger" departSpeed="max"/>
    <trip id="veh333" depart="2725.20" from="96236048#7" to="161964128#5" departLane="best" type="veh_passenger"/>
    <trip id="veh334" depart="2733.39" from="-161964128#12" to="208944503" departLane="best" type="veh_passenger" departSpeed="max"/>
    <trip id="veh335" depart="2741.57" from="208944641#4" to="803850493#1" departLane="best" type="veh_passenger"/>
    <trip id="veh336" depart="2749.76" from="483862438" to="-96235897#3" departLane="best" type="veh_passenger" departSpeed="max"/>
    <trip id="veh337" depart="2757.94" from="208957241#0" to="-208957209#1" departLane="best" type="veh_passenger"/>
    <trip id="veh338" depart="2766.12" from="-96236048#5" to="96236010#3" departLane="best" type="veh_passenger"/>
    <trip id="veh339" depart="2774.31" from="-800384656" to="208957237#1" departLane="best" type="veh_passenger" departSpeed="max"/>
    <trip id="veh340" depart="2782.49" from="208957229#1" to="803569311#2" departLane="best" type="veh_passenger"/>
    <trip id="veh341" depart="2790.67" from="803850502" to="803757415" departLane="best" type="veh_passenger" departSpeed="max"/>
    <trip id="veh342" depart="2798.86" from="804561973#0" to="-208944513" departLane="best" type="veh_passenger" departSpeed="max"/>
    <trip id="veh343" depart="2807.04" from="-208944549#1" to="208944670#0" departLane="best" type="veh_passenger"/>
    <trip id="veh344" depart="2815.23" from="84168568#5" to="96236068#5" departLane="best" type="veh_passenger"/>
    <trip id="veh345" depart="2823.41" from="483862455#0" to="-96235956#0" departLane="best" type="veh_passenger" departSpeed="max"/>
    <trip id="veh346" depart="2831.59" from="-208944597" to="208944670#0" departLane="best" type="veh_passenger" departSpeed="max"/>
    <trip id="veh347" depart="2839.78" from="804561973#0" to="-96236048#0" departLane="best" type="veh_passenger" departSpeed="max"/>
    <trip id="veh348" depart="2847.96" from="-161964128#7" to="800324738" departLane="best" type="veh_passenger"/>
    <trip id="veh349" depart="2856.15" from="-800316119" to="-84168568#1" departLane="best" type="veh_passenger"/>
    <trip id="veh350" depart="2864.33" from="208944615#0" to="800324736" departLane="best" type="veh_passenger"/>
    <trip id="veh351" depart="2872.51" from="-208944670#1" to="-208944606#0" departLane="best" type="veh_passenger" departSpeed="max"/>
    <trip id="veh352" depart="2880.70" from="804561973#0" to="208944656#6" departLane="best" type="veh_passenger" departSpeed="max"/>
    <trip id="veh353" depart="2888.88" from="-208944641#3" to="1076498443" departLane="best" type="veh_passenger"/>
    <trip id="veh354" depart="2897.06" from="-227850831" to="-483862449#0" departLane="best" type="veh_passenger"/>
    <trip id="veh355" depart="2905.25" from="-208944656#6" to="-96236010#5" departLane="best" type="veh_passenger" departSpeed="max"/>
    <trip id="veh356" depart="2913.43" from="-800593535" to="208944625#1" departLane="best" type="veh_passenger" departSpeed="max"/>
    <trip id="veh357" depart="2921.62" from="-208957274#0" to="803569310#0" departLane="best" type="veh_passenger"/>
    <trip id="veh358" depart="2929.80" from="-208944699#4" to="-84168568#2" departLane="best" type="veh_passenger"/>
    <trip id="veh359" depart="2937.98" from="1220116022" to="-483862437#0" departLane="best" type="veh_passenger"/>
    <trip id="veh360" depart="2946.17" from="208944623#2" to="208944606#1" departLane="best" type="veh_passenger"/>
    <trip id="veh361" depart="2954.35" from="96236068#3" to="-800324737" departLane="best" type="veh_passenger"/>
    <trip id="veh362" depart="2962.53" from="96236048#5" to="208944699#2" departLane="best" type="veh_passenger"/>
    <trip id="veh363" depart="2970.72" from="-483862446#1" to="208944605#0" departLane="best" type="veh_passenger"/>
    <trip id="veh364" depart="2978.90" from="208957283" to="32111480#5" departLane="best" type="veh_passenger" departSpeed="max"/>
    <trip id="veh365" depart="2987.09" from="-208944503" to="208944646#1" departLane="best" type="veh_passenger"/>
    <trip id="veh366" depart="2995.27" from="161964128#6" to="804561973#4" departLane="best" type="veh_passenger"/>
    <trip id="veh367" depart="3003.45" from="208944656#4" to="-803757414" departLane="best" type="veh_passenger"/>
    <trip id="veh368" depart="3011.64" from="208957209#1" to="208944656#6" departLane="best" type="veh_passenger"/>
    <trip id="veh369" depart="3019.82" from="208957246#1" to="803569305" departLane="best" type="veh_passenger"/>
    <trip id="veh370" depart="3028.00" from="-96235897#0" to="208944615#0" departLane="best" type="veh_passenger"/>
    <trip id="veh371" depart="3036.19" from="483862446#1" to="-208944615#1" departLane="best" type="veh_passenger"/>
    <trip id="veh372" depart="3044.37" from="-800316120" to="32111480#5" departLane="best" type="veh_passenger" departSpeed="max"/>
    <trip id="veh373" depart="3052.56" from="208944593#0" to="96236010#5" departLane="best" type="veh_passenger" departSpeed="max"/>
    <trip id="veh374" depart="3060.74" from="208944579#0" to="804561974#3" departLane="best" type="veh_passenger"/>
    <trip id="veh375" depart="3068.92" from="803569311#2" to="161964128#10" departLane="best" type="veh_passenger"/>
    <trip id="veh376" depart="3077.11" from="800357600#0" to="32111480#5" departLane="best" type="veh_passenger"/>
    <trip id="veh377" depart="3085.29" from="-800384656" to="-208944656#0" departLane="best" type="veh_passenger" departSpeed="max"/>
    <trip id="veh378" depart="3093.48" from="96235956#0" to="-208944682#2" departLane="best" type="veh_passenger" departSpeed="max"/>
    <trip id="veh379" depart="3101.66" from="96236010#0" to="803757415" departLane="best" type="veh_passenger"/>
    <trip id="veh380" depart="3109.84" from="483862438" to="96236048#7" departLane="best" type="veh_passenger" departSpeed="max"/>
    <trip id="veh381" depart="3118.03" from="96236010#0" to="800324743" departLane="best" type="veh_passenger"/>
    <trip id="veh382" depart="3126.21" from="-1200726406" to="208944570#1" departLane="best" type="veh_passenger" departSpeed="max"/>
    <trip id="veh383" depart="3134.39" from="-96235945#4" to="208957209#7" departLane="best" type="veh_passenger"/>
    <trip id="veh384" depart="3142.58" from="208957267#2" to="208944623#1" departLane="best" type="veh_passenger"/>
    <trip id="veh385" depart="3150.76" from="803569311#0" to="84168568#7" departLane="best" type="veh_passenger"/>
    <trip id="veh386" depart="3158.95" from="-208944600" to="-483862437#0" departLane="best" type="veh_passenger" departSpeed="max"/>
    <trip id="veh387" depart="3167.13" from="208944606#0" to="804561974#4" departLane="best" type="veh_passenger" departSpeed="max"/>
    <trip id="veh388" depart="3175.31" from="-208957229#2" to="-208944593#0" departLane="best" type="veh_passenger" departSpeed="max"/>
    <trip id="veh389" depart="3183.50" from="803569311#1" to="804561974#0" departLane="best" type="veh_passenger"/>
    <trip id="veh390" depart="3191.68" from="-800324731" to="-96235897#2" departLane="best" type="veh_passenger"/>
    <trip id="veh391" depart="3199.86" from="-208944641#0" to="84168568#9" departLane="best" type="veh_passenger"/>
    <trip id="veh392" depart="3208.05" from="-208944597" to="803850499" departLane="best" type="veh_passenger" departSpeed="max"/>
    <trip id="veh393" depart="3216.23" from="-208944635#1" to="-96236048#9" departLane="best" type="veh_passenger"/>
    <trip id="veh394" depart="3224.42" from="208957267#1" to="32111480#4" departLane="best" type="veh_passenger"/>
    <trip id="veh395" depart="3232.60" from="483862455#0" to="-208957209#1" departLane="best" type="veh_passenger" departSpeed="max"/>
    <trip id="veh396" depart="3240.78" from="-84168568#11" to="-208944630#1" departLane="best" type="veh_passenger"/>
    <trip id="veh397" depart="3248.97" from="161964128#10" to="-96235897#2" departLane="best" type="veh_passenger"/>
    <trip id="veh398" depart="3257.15" from="96235944#7" to="-208944511" departLane="best" type="veh_passenger"/>
    <trip id="veh399" depart="3265.34" from="-803569310#2" to="-96236048#0" departLane="best" type="veh_passenger"/>
    <trip id="veh400" depart="3273.52" from="96235944#6" to="803569312" departLane="best" type="veh_passenger"/>
    <trip id="veh401" depart="3281.70" from="-208944597" to="208957237#0" departLane="best" type="veh_passenger" departSpeed="max"/>
    <trip id="veh402" depart="3289.89" from="208944598#1" to="96236048#5" departLane="best" type="veh_passenger"/>
    <trip id="veh403" depart="3298.07" from="-800593540" to="-84168568#7" departLane="best" type="veh_passenger" departSpeed="max"/>
    <trip id="veh404" depart="3306.25" from="803850502" to="1059873643" departLane="best" type="veh_passenger" departSpeed="max"/>
    <trip id="veh405" depart="3314.44" from="208957266" to="208944679#3" departLane="best" type="veh_passenger" departSpeed="max"/>
    <trip id="veh406" depart="3322.62" from="208944656#0" to="-161964128#4" departLane="best" type="veh_passenger" departSpeed="max"/>
    <trip id="veh407" depart="3330.81" from="800324742" to="-483862438" departLane="best" type="veh_passenger" departSpeed="max"/>
    <trip id="veh408" depart="3338.99" from="-208944623#1" to="208944600" departLane="best" type="veh_passenger"/>
    <trip id="veh409" depart="3347.17" from="-208944549#1" to="800316117#0" departLane="best" type="veh_passenger"/>
    <trip id="veh410" depart="3355.36" from="-208957209#4" to="-32111480#3" departLane="best" type="veh_passenger"/>
    <trip id="veh411" depart="3363.54" from="804561973#0" to="-800357600#0" departLane="best" type="veh_passenger" departSpeed="max"/>
    <trip id="veh412" depart="3371.72" from="-208944646#3" to="803853166" departLane="best" type="veh_passenger"/>
    <trip id="veh413" depart="3379.91" from="-1075652205#0" to="803569312" departLane="best" type="veh_passenger"/>
    <trip id="veh414" depart="3388.09" from="-208944646#0" to="-208944663#0" departLane="best" type="veh_passenger"/>
    <trip id="veh415" depart="3396.28" from="-208957274#1" to="-208957241#1" departLane="best" type="veh_passenger"/>
    <trip id="veh416" depart="3404.46" from="208957247" to="-161964128#8" departLane="best" type="veh_passenger"/>
    <trip id="veh417" depart="3412.64" from="-1200726406" to="800324733" departLane="best" type="veh_passenger" departSpeed="max"/>
    <trip id="veh418" depart="3420.83" from="-208957246#0" to="-800344956" departLane="best" type="veh_passenger"/>
    <trip id="veh419" depart="3429.01" from="-208944670#1" to="-208944565#1" departLane="best" type="veh_passenger" departSpeed="max"/>
    <trip id="veh420" depart="3437.19" from="483862455#0" to="1220118991" departLane="best" type="veh_passenger" departSpeed="max"/>
    <trip id="veh421" depart="3445.38" from="-208944600" to="208944506" departLane="best" type="veh_passenger" departSpeed="max"/>
    <trip id="veh422" depart="3453.56" from="96235944#0" to="-208944549#0" departLane="best" type="veh_passenger" departSpeed="max"/>
    <trip id="veh423" depart="3461.75" from="800324740#1" to="803850471#0" departLane="best" type="veh_passenger"/>
    <trip id="veh424" depart="3469.93" from="208944549#1" to="1075652204" departLane="best" type="veh_passenger"/>
    <trip id="veh425" depart="3478.11" from="96235956#0" to="-208944593#0" departLane="best" type="veh_passenger" departSpeed="max"/>
    <trip id="veh426" depart="3486.30" from="1075652204" to="-84168568#8" departLane="best" type="veh_passenger"/>
    <trip id="veh427" depart="3494.48" from="227850831" to="161964128#12" departLane="best" type="veh_passenger"/>
    <trip id="veh428" depart="3502.67" from="84168568#11" to="-208944602" departLane="best" type="veh_passenger"/>
    <trip id="veh429" depart="3510.85" from="-208944568" to="208944646#2" departLane="best" type="veh_passenger"/>
    <trip id="veh430" depart="3519.03" from="-208944546" to="-800316115" departLane="best" type="veh_passenger" departSpeed="max"/>
    <trip id="veh431" depart="3527.22" from="208944699#3" to="208944593#1" departLane="best" type="veh_passenger"/>
    <trip id="veh432" depart="3535.40" from="-800344954#1" to="96236068#4" departLane="best" type="veh_passenger"/>
    <trip id="veh433" depart="3543.58" from="208944656#3" to="-208944630#1" departLane="best" type="veh_passenger"/>
    <trip id="veh434" depart="3551.77" from="32111480#3" to="803569312" departLane="best" type="veh_passenger"/>
    <trip id="veh435" depart="3559.95" from="208957237#0" to="800316117#1" departLane="best" type="veh_passenger"/>
    <trip id="veh436" depart="3568.14" from="483862438" to="-32111480#2" departLane="best" type="veh_passenger" departSpeed="max"/>
    <trip id="veh437" depart="3576.32" from="-96235944#8" to="-483862436" departLane="best" type="veh_passenger"/>
    <trip id="veh438" depart="3584.50" from="-800384656" to="-96236048#9" departLane="best" type="veh_passenger" departSpeed="max"/>
    <trip id="veh439" depart="3592.69" from="-84168568#11" to="-208944625#1" departLane="best" type="veh_passenger"/>
</routes>
